Metadata-Version: 2.3
Name: mcp-server-ancestry
Version: 0.1.1
Summary: A Model Context Protocol server providing functionality to GEDCOM files via LLM usage
Author: Robert Oxley
Maintainer-email: Robert Oxley <robbie@oxley.ca>
License: MIT
Keywords: automation,llm,mcp
Classifier: Development Status :: 4 - Beta
Classifier: Intended Audience :: Developers
Classifier: License :: OSI Approved :: MIT License
Classifier: Programming Language :: Python :: 3
Classifier: Programming Language :: Python :: 3.10
Requires-Python: >=3.10
Requires-Dist: chardet>=5.2.0
Requires-Dist: mcp>=1.0.0
Requires-Dist: pydantic>=2.0.0
Requires-Dist: requests>=2.32.3
